{
  "name": "scrollyeah",
  "title": "Scrollyeah",
  "description": "Puts floats in single line.",
  "keywords": [
		"ui",
		"responsive",
		"slider",
		"carousel",
		"content",
    "scroll",
    "layout",
    "animation"
	],
  "version": "0.3.2",
  "homepage": "https://github.com/artpolikarpov/scrollyeah",
  "author": {
    "name": "Artem Polikarpov",
    "email": "artpolikarpov@gmail.com"
  },
  "repository": {
    "type": "git",
    "url": "git://github.com/artpolikarpov/scrollyeah.git"
  },
  "bugs": "https://github.com/artpolikarpov/scrollyeah/issues",
  "licenses": [
    {
      "type": "MIT",
      "url": "https://github.com/artpolikarpov/scrollyeah/blob/master/LICENSE-MIT"
    }
  ],
  "dependencies": {
    "jquery": ">=1.8"
  }
}